crawl_wx/__init__.py
crawl_wx/cmd.py
crawl_wx/crawl.py
crawl_wx/exception.py
crawl_wx/util.py
crawl_wx-0.0.8.dist-info/METADATA
crawl_wx-0.0.8.dist-info/WHEEL
crawl_wx-0.0.8.dist-info/entry_points.txt
crawl_wx-0.0.8.dist-info/top_level.txt
crawl_wx-0.0.8.dist-info/RECORD
