Metadata-Version: 2.1
Name: crawl-wx
Version: 0.0.8
Summary: crawl wechat public account contents
Home-page: https://github.com/fatelei/crawl_wx
Author: fatelei
Author-email: fatelei@gmail.com
License: PRIVATE
Platform: UNKNOWN
Requires-Dist: uncurl
Requires-Dist: requests
Requires-Dist: beautifulsoup4
